flloat/__init__.py
flloat/__version__.py
flloat/base.py
flloat/delta.py
flloat/flloat.py
flloat/helpers.py
flloat/ldlf.py
flloat/ltlf.py
flloat/pl.py
flloat/symbols.py
flloat/parser/__init__.py
flloat/parser/ldlf.lark
flloat/parser/ldlf.py
flloat/parser/ltlf.lark
flloat/parser/ltlf.py
flloat/parser/pl.lark
flloat/parser/pl.py
flloat-0.3.0.data/data/flloat/parser/ldlf.lark
flloat-0.3.0.data/data/flloat/parser/ltlf.lark
flloat-0.3.0.data/data/flloat/parser/pl.lark
flloat-0.3.0.dist-info/LICENSE
flloat-0.3.0.dist-info/METADATA
flloat-0.3.0.dist-info/WHEEL
flloat-0.3.0.dist-info/top_level.txt
flloat-0.3.0.dist-info/RECORD
