Metadata-Version: 2.1
Name: flloat
Version: 0.3.0
Summary: A Python implementation of the FLLOAT library.
Home-page: https://github.com/whitemech/flloat.git
Author: Marco Favorito
Author-email: marco.favorito@gmail.com
License: Apache license
Keywords: flloat
Platform: UNKNOWN
Classifier: Development Status :: 2 - Pre-Alpha
Classifier: Intended Audience :: Developers
Classifier: License :: OSI Approved :: Apache Software License
Classifier: Natural Language :: English
Classifier: Programming Language :: Python :: 3
Classifier: Programming Language :: Python :: 3.6
Classifier: Programming Language :: Python :: 3.7
Requires-Dist: lark-parser
Requires-Dist: pythomata (>=0.3.2)
Requires-Dist: sympy
